gnomeunlock/__init__.py
gnomeunlock/unlock.py
gnome_keyring_unlock-1.0.dist-info/LICENSE
gnome_keyring_unlock-1.0.dist-info/METADATA
gnome_keyring_unlock-1.0.dist-info/WHEEL
gnome_keyring_unlock-1.0.dist-info/entry_points.txt
gnome_keyring_unlock-1.0.dist-info/top_level.txt
gnome_keyring_unlock-1.0.dist-info/RECORD
