Metadata-Version: 2.1
Name: gnome-keyring-unlock
Version: 1.0
Summary: Unlock GNOME Password
Home-page: https://codeberg.org/gweatherby/gnome-keyring-unlock
Author: Håvard Moen
Author-email: post@haavard.name
Maintainer: Gerard Weatherby
Maintainer-email: gerardw@alum.mit.edu
License: GPL-3.0-only
License-File: LICENSE
